openai_multi_client/__init__.py
openai_multi_client-0.1.1.dist-info/LICENSE
openai_multi_client-0.1.1.dist-info/METADATA
openai_multi_client-0.1.1.dist-info/WHEEL
openai_multi_client-0.1.1.dist-info/top_level.txt
openai_multi_client-0.1.1.dist-info/RECORD
