Metadata-Version: 2.1
Name: openai-multi-client
Version: 0.1.1
Summary: A parallel client for OpenAI API (and more)
Author-email: Ziyang Hu <hu.ziyang@cantab.net>
License: MIT
Keywords: openai,client
Classifier: Programming Language :: Python :: 3
Requires-Python: >=3.7
License-File: LICENSE
Requires-Dist: openai
Requires-Dist: tenacity
Requires-Dist: aioprocessing
